nextdnsctl/__init__.py
nextdnsctl/api.py
nextdnsctl/config.py
nextdnsctl/nextdnsctl.py
nextdnsctl-1.2.0.dist-info/licenses/LICENSE
tests/__init__.py
tests/conftest.py
tests/test_api_resilience.py
tests/test_cli_integration.py
tests/test_concurrency.py
tests/test_config.py
tests/test_parsing.py
tests/test_validation.py
nextdnsctl-1.2.0.dist-info/METADATA
nextdnsctl-1.2.0.dist-info/WHEEL
nextdnsctl-1.2.0.dist-info/entry_points.txt
nextdnsctl-1.2.0.dist-info/top_level.txt
nextdnsctl-1.2.0.dist-info/RECORD
