Metadata-Version: 2.4
Name: nextdnsctl
Version: 1.2.0
Summary: A CLI tool for managing NextDNS profiles
Home-page: https://github.com/danielmeint/nextdnsctl
Author: Daniel Meint
Author-email: pilots-4-trilogy@icloud.com
License: MIT
Keywords: nextdns,cli,dns,security,networking
Classifier: Development Status :: 5 - Production/Stable
Classifier: License :: OSI Approved :: MIT License
Classifier: Programming Language :: Python :: 3
Classifier: Programming Language :: Python :: 3.10
Classifier: Programming Language :: Python :: 3.11
Classifier: Programming Language :: Python :: 3.12
Requires-Python: >=3.10
License-File: LICENSE
Requires-Dist: requests
Requires-Dist: click
Dynamic: author
Dynamic: author-email
Dynamic: classifier
Dynamic: description
Dynamic: description-content-type
Dynamic: home-page
Dynamic: keywords
Dynamic: license
Dynamic: license-file
Dynamic: requires-dist
Dynamic: requires-python
Dynamic: summary
